{
  "hash": "89a52947",
  "configHash": "577f490b",
  "lockfileHash": "134e0f58",
  "browserHash": "266104f0",
  "optimized": {
    "react/jsx-dev-runtime": {
      "src": "../../node_modules/react/jsx-dev-runtime.js",
      "file": "react_jsx-dev-runtime.js",
      "fileHash": "591e4d6e",
      "needsInterop": true
    },
    "react": {
      "src": "../../node_modules/react/index.js",
      "file": "react.js",
      "fileHash": "17dc7198",
      "needsInterop": true
    },
    "react-dom/client": {
      "src": "../../node_modules/react-dom/client.js",
      "file": "react-dom_client.js",
      "fileHash": "55308834",
      "needsInterop": true
    },
    "@chakra-ui/react": {
      "src": "../../node_modules/@chakra-ui/react/dist/esm/index.mjs",
      "file": "@chakra-ui_react.js",
      "fileHash": "9cf3c33c",
      "needsInterop": false
    },
    "react-router-dom": {
      "src": "../../node_modules/react-router-dom/dist/index.js",
      "file": "react-router-dom.js",
      "fileHash": "7d7a951f",
      "needsInterop": false
    },
    "framer-motion": {
      "src": "../../node_modules/framer-motion/dist/es/index.mjs",
      "file": "framer-motion.js",
      "fileHash": "463f4024",
      "needsInterop": false
    },
    "react-confetti": {
      "src": "../../node_modules/react-confetti/dist/react-confetti.mjs",
      "file": "react-confetti.js",
      "fileHash": "00df4a1a",
      "needsInterop": false
    },
    "react-icons/fa": {
      "src": "../../node_modules/react-icons/fa/index.mjs",
      "file": "react-icons_fa.js",
      "fileHash": "16ca6980",
      "needsInterop": false
    }
  },
  "chunks": {
    "chunk-YUNTBJI6": {
      "file": "chunk-YUNTBJI6.js"
    },
    "chunk-WBI553HU": {
      "file": "chunk-WBI553HU.js"
    },
    "chunk-UOND5N6D": {
      "file": "chunk-UOND5N6D.js"
    },
    "chunk-45FXRYJS": {
      "file": "chunk-45FXRYJS.js"
    }
  }
}